{"id":"965b5cb6-29bd-4a91-a2bc-6098f30d5b8b","timestamp":1767686932642,"matcher":{"static":{"/__nuxt_content/content/sql_dump.txt":{"prerender":true}},"wildcard":{},"dynamic":{}},"prerendered":["/","/docs","/docs/quick-start","/deploy","/config","/docs/plugins","/docs/nightly","/docs/migration","/docs/cache","/deploy/runtimes/node","/docs/lifecycle","/docs/assets","/docs/database","/docs/storage","/docs/routing","/docs/tasks","/docs/renderer","/docs/server-entry","/docs/configuration","/deploy/providers/firebase","/deploy/providers/netlify","/deploy/providers/stormkit","/deploy/providers/azure","/deploy/providers/aws-amplify","/deploy/providers/zeabur","/deploy/runtimes/bun","/deploy/runtimes/deno","/deploy/providers/cleavr","/deploy/providers/aws","/deploy/providers/deno-deploy","/deploy/providers/digitalocean","/deploy/providers/alwaysdata","/deploy/providers/flightcontrol","/deploy/providers/genezio","/deploy/providers/github-pages","/deploy/providers/gitlab-pages","/deploy/providers/vercel","/deploy/providers/cloudflare","/deploy/providers/iis","/deploy/providers/heroku","/deploy/providers/koyeb","/deploy/providers/platform-sh","/deploy/providers/zerops","/deploy/providers/render"]}